mcplaywright/__init__.py
mcplaywright/cli.py
mcplaywright/context.py
mcplaywright/differential_snapshots.py
mcplaywright/middleware.py
mcplaywright/request_interceptor.py
mcplaywright/server.py
mcplaywright/server_comprehensive.py
mcplaywright/session_manager.py
mcplaywright/collaboration/__init__.py
mcplaywright/collaboration/element_inspector.py
mcplaywright/collaboration/messaging.py
mcplaywright/collaboration/optimized_scripts.py
mcplaywright/collaboration/secure_v8_scripts.py
mcplaywright/collaboration/user_prompts.py
mcplaywright/collaboration/voice_communication.py
mcplaywright/filters/__init__.py
mcplaywright/filters/decorators.py
mcplaywright/filters/engine.py
mcplaywright/filters/models.py
mcplaywright/models/__init__.py
mcplaywright/models/console.py
mcplaywright/models/request.py
mcplaywright/modules/__init__.py
mcplaywright/modules/browser.py
mcplaywright/modules/client_id.py
mcplaywright/modules/coordinates.py
mcplaywright/modules/extension_management.py
mcplaywright/modules/firefox_extension_management.py
mcplaywright/modules/interaction.py
mcplaywright/modules/media_stream.py
mcplaywright/modules/navigation.py
mcplaywright/modules/screenshots.py
mcplaywright/modules/system.py
mcplaywright/pagination/__init__.py
mcplaywright/pagination/cursor_manager.py
mcplaywright/pagination/decorators.py
mcplaywright/pagination/models.py
mcplaywright/pagination/pagination_manager.py
mcplaywright/pagination/storage.py
mcplaywright/pagination/utils.py
mcplaywright/state/__init__.py
mcplaywright/state/devtools_state.py
mcplaywright/tools/__init__.py
mcplaywright/tools/advanced_mouse.py
mcplaywright/tools/artifacts.py
mcplaywright/tools/browser.py
mcplaywright/tools/collaboration.py
mcplaywright/tools/configure.py
mcplaywright/tools/devtools.py
mcplaywright/tools/dialogs.py
mcplaywright/tools/evaluation.py
mcplaywright/tools/firefox_devtools.py
mcplaywright/tools/interaction.py
mcplaywright/tools/message_queue_tools.py
mcplaywright/tools/mobile_emulation.py
mcplaywright-0.2.6.dist-info/METADATA
mcplaywright-0.2.6.dist-info/WHEEL
mcplaywright-0.2.6.dist-info/entry_points.txt
mcplaywright-0.2.6.dist-info/RECORD
