Metadata-Version: 2.4
Name: mcplaywright
Version: 0.2.6
Summary: Python Playwright MCP Server with FastMCP 2.0 - Advanced browser automation with video recording, request monitoring, and UI customization
Project-URL: Homepage, https://github.com/mcplaywright/mcplaywright
Project-URL: Documentation, https://mcplaywright.github.io/docs
Project-URL: Repository, https://github.com/mcplaywright/mcplaywright
Project-URL: Bug Tracker, https://github.com/mcplaywright/mcplaywright/issues
Author-email: Ryan Malloy <ryan@supported.systems>
License: Apache-2.0
Keywords: automation,browser,fastmcp,mcp,playwright
Classifier: Development Status :: 4 - Beta
Classifier: Intended Audience :: Developers
Classifier: License :: OSI Approved :: Apache Software License
Classifier: Operating System :: OS Independent
Classifier: Programming Language :: Python :: 3
Classifier: Programming Language :: Python :: 3.11
Classifier: Programming Language :: Python :: 3.12
Classifier: Programming Language :: Python :: 3.13
Classifier: Topic :: Internet :: WWW/HTTP :: Browsers
Classifier: Topic :: Software Development :: Libraries :: Python Modules
Classifier: Topic :: Software Development :: Testing
Requires-Python: >=3.11
Requires-Dist: aiosqlite>=0.20.0
Requires-Dist: fastmcp>=2.12.5
Requires-Dist: playwright>=1.55.0
Requires-Dist: pydantic>=2.11.7
Requires-Dist: requests>=2.31.0
Provides-Extra: cli
Requires-Dist: click>=8.1.0; extra == 'cli'
Requires-Dist: rich>=13.7.0; extra == 'cli'
Provides-Extra: dev
Requires-Dist: black>=23.0.0; extra == 'dev'
Requires-Dist: hatchling>=1.18.0; extra == 'dev'
Requires-Dist: httpx>=0.25.0; extra == 'dev'
Requires-Dist: isort>=5.12.0; extra == 'dev'
Requires-Dist: mypy>=1.8.0; extra == 'dev'
Requires-Dist: pytest-asyncio>=1.1.0; extra == 'dev'
Requires-Dist: pytest-benchmark>=4.0.0; extra == 'dev'
Requires-Dist: pytest-cov>=4.0.0; extra == 'dev'
Requires-Dist: pytest-html>=4.1.0; extra == 'dev'
Requires-Dist: pytest>=8.4.0; extra == 'dev'
Requires-Dist: ruff>=0.1.0; extra == 'dev'
Requires-Dist: uvicorn>=0.24.0; extra == 'dev'
Requires-Dist: watchfiles>=0.21.0; extra == 'dev'
Provides-Extra: docs
Requires-Dist: mkdocs-material>=9.4.0; extra == 'docs'
Requires-Dist: mkdocs-mermaid2-plugin>=1.1.0; extra == 'docs'
Requires-Dist: mkdocs>=1.5.0; extra == 'docs'
Provides-Extra: firefox
Requires-Dist: geckordp>=1.0.3; extra == 'firefox'
Provides-Extra: image-processing
Requires-Dist: pillow>=10.4.0; extra == 'image-processing'
Provides-Extra: performance
Requires-Dist: memory-profiler>=0.61.0; extra == 'performance'
Requires-Dist: psutil>=5.9.0; extra == 'performance'
Requires-Dist: py-spy>=0.3.14; extra == 'performance'
Provides-Extra: system-control
Requires-Dist: pyautogui>=0.9.54; extra == 'system-control'
